pymtpng/__init__.py
pymtpng/py.typed
pymtpng/pymtpng.pyd
pymtpng/pymtpng.pyi
pymtpng-1.0.4.dist-info/METADATA
pymtpng-1.0.4.dist-info/WHEEL
pymtpng-1.0.4.dist-info/licenses/LICENSE
pymtpng-1.0.4.dist-info/RECORD
