Metadata-Version: 2.1
Name: pymtpng
Version: 1.0.4
Summary: Python bindings for MTPNG library
Author-Email: =?utf-8?q?Peter_W=C3=BCrtz?= <pwuertz@gmail.com>
Classifier: License :: OSI Approved :: MIT License
Project-URL: Homepage, https://github.com/pwuertz/pymtpng
Requires-Python: >=3.9
